search_weather/__init__.py
search_weather/get_weather.py
search_weather/main.py
search_weather/parse_query.py
search_weather/scripts.py
search_weather-0.1.3.dist-info/LICENSE
search_weather-0.1.3.dist-info/METADATA
search_weather-0.1.3.dist-info/WHEEL
search_weather-0.1.3.dist-info/top_level.txt
search_weather-0.1.3.dist-info/RECORD
