Metadata-Version: 2.1
Name: search_weather
Version: 0.1.3
Summary: A package for searching weather information
Home-page: https://github.com/minarae/search_weather
Author: minarae
Author-email: minarae@gmail.com
Classifier: Programming Language :: Python :: 3
Classifier: License :: OSI Approved :: MIT License
Classifier: Operating System :: OS Independent
Requires-Python: >=3.11
License-File: LICENSE
Requires-Dist: requests
Requires-Dist: geopy
Requires-Dist: spacy <4.0.0,>=3.8.2
Provides-Extra: dev
Requires-Dist: pytest ; extra == 'dev'
Requires-Dist: flake8 ; extra == 'dev'
